pdf_outline/__init__.py
pdf_outline/main.py
pdf_outline/pdf.py
pdf_outline_tool-0.0.3.dist-info/METADATA
pdf_outline_tool-0.0.3.dist-info/WHEEL
pdf_outline_tool-0.0.3.dist-info/entry_points.txt
pdf_outline_tool-0.0.3.dist-info/top_level.txt
pdf_outline_tool-0.0.3.dist-info/RECORD
