Metadata-Version: 2.1
Name: pdf-outline-tool
Version: 0.0.3
Summary: Extract or add pdf outline
Home-page: https://github.com/xirenhua/pdf_outline
Author: xirenhua
Author-email: xirenhua@outlook.com
Requires-Dist: PyPDF2
Requires-Dist: click
